lesync/__init__.py
lesync/core.py
lesync/trafaret.py
lesync/utils.py
lesync-0.4.0.dist-info/LICENSE
lesync-0.4.0.dist-info/METADATA
lesync-0.4.0.dist-info/WHEEL
lesync-0.4.0.dist-info/top_level.txt
lesync-0.4.0.dist-info/RECORD
