Metadata-Version: 2.1
Name: lesync
Version: 0.4.0
Summary: Http helpers for django-channels
Home-page: https://github.com/imbolc/lesync
Author: Imbolc
Author-email: imbolc@imbolc.name
License: MIT
Platform: UNKNOWN
Classifier: Development Status :: 4 - Beta
Classifier: License :: OSI Approved :: MIT License
Classifier: Programming Language :: Python :: 3
Classifier: Operating System :: OS Independent
Requires-Dist: django
Requires-Dist: channels
